LICENSE.txt
README.md
setup.cfg
setup.py
pronto_commons/__init__.py
pronto_commons/aws.py
pronto_commons/check_correspondence.py
pronto_commons/dates.py
pronto_commons/entities.py
pronto_commons/env.py
pronto_commons/exceptions.py
pronto_commons/flask.py
pronto_commons/images.py
pronto_commons/jwt.py
pronto_commons/marshmallow.py
pronto_commons/mongo.py
pronto_commons/sentry.py
pronto_commons/utils.py
pronto_commons.egg-info/PKG-INFO
pronto_commons.egg-info/SOURCES.txt
pronto_commons.egg-info/dependency_links.txt
pronto_commons.egg-info/top_level.txt