Metadata-Version: 2.1
Name: pronto-commons
Version: 0.0.19
Summary: Pronto common methods and entities used on the products backend
Home-page: https://bitbucket.org/tuprontomx/pronto_commons
Author: Pronto development <dev@tupronto.mx>
Author-email: dev@tupronto.mx
License: MIT
Keywords: Pronto,Commons
Platform: UNKNOWN
Classifier: Development Status :: 3 - Alpha
Classifier: Intended Audience :: Developers
Classifier: Topic :: Software Development :: Build Tools
Classifier: License :: OSI Approved :: MIT License
Classifier: Programming Language :: Python :: 3
Classifier: Programming Language :: Python :: 3.4
Classifier: Programming Language :: Python :: 3.5
Classifier: Programming Language :: Python :: 3.6
Classifier: Programming Language :: Python :: 3.7
Classifier: Programming Language :: Python :: 3.8
Classifier: Programming Language :: Python :: 3.9
Requires-Python: >=3
License-File: LICENSE.txt
